Metadata-Version: 2.1
Name: Selen-utils
Version: 0.4
Summary: Selenium_template_utils
Author-email: alisbivalka@gmail.com
